Metadata-Version: 2.1
Name: nonebot-plugin-bilibilicover
Version: 0.1.0
Summary: 通过发送视频 AV 或 BV 号来获取视频封面图
Home-page: https://github.com/kamuxiy/nonebot-plugin-bilibilicover
Author: kamuXiY
Author-email: 1711087540@qq.com
License: MIT
Platform: UNKNOWN
Classifier: License :: OSI Approved :: MIT License
Classifier: Programming Language :: Python
Classifier: Programming Language :: Python :: 3
Classifier: Programming Language :: Python :: 3.6
Classifier: Programming Language :: Python :: Implementation :: CPython
Classifier: Programming Language :: Python :: Implementation :: PyPy
Requires-Python: >=3.8.0
Requires-Dist: nonebot2
Requires-Dist: urllib3
Requires-Dist: json
